DESCRIPTION.rst
LICENSE
MANIFEST.in
README.md
setup.py
metal/__init__.py
metal/_version.py
metal/about.py
metal/bash_init.py
metal/chk_standalone.py
metal/chkrootkit.py
metal/chkrootkit_parser.py
metal/cli.py
metal/colors.py
metal/help_menu.py
metal/logd.py
metal/oscodes_unix.py
metal/script_utils.py
metal/statics.py
metal/rkhunter/__init__.py
metal/rkhunter/rkinstaller.sh
metal/rkhunter/config/README.md
metal/rkhunter/config/cron.daily
metal/rkhunter/config/rkhunter.conf
metal/rkhunter/core/_version.sh
metal/rkhunter/core/colors.sh
metal/rkhunter/core/configure_perl.sh
metal/rkhunter/core/configure_skdet.sh
metal/rkhunter/core/configure_unhide.sh
metal/rkhunter/core/exitcodes.sh
metal/rkhunter/core/list-modules.pl
metal/rkhunter/core/os_distro.sh
metal/rkhunter/core/std_functions.sh
metal/rkhunter/skdet/README.md
metal/rkhunter/skdet/skdet-1.0.sha1
metal/rkhunter/skdet/skdet-1.0.tar.bz2
metal/rkhunter/skdet/skdet-fix-includes.diff
metal/rkhunter/unhide/README.md
metal/rkhunter/unhide/unhide_20130526.orig.tar.gz