Metadata-Version: 1.2
Name: metal
Version: 3.1.0.1
Summary: Security App Installation & Configuration
Home-page: https://github.com/fstab50/metal
Author: Blake Huber
Author-email: blakeca00@gmail.com
License: MIT
Keywords: Security tools installation configure Amazon Web Services AWS tools s3
Platform: UNKNOWN
Classifier: Topic :: Security
Classifier: Topic :: System :: Systems Administration
Classifier: Topic :: Utilities
Classifier: Development Status :: 4 - Beta
Classifier: Programming Language :: Python :: 3.4
Classifier: Programming Language :: Python :: 3.5
Classifier: Programming Language :: Python :: 3.6
Classifier: License :: OSI Approved :: GNU General Public License v3 (GPLv3)
Classifier: Operating System :: POSIX :: Linux
Requires-Python: >=3.4, <4
